LICENSE
README.txt
setup.py
zdeskcfg.py
zdeskcfg.egg-info/PKG-INFO
zdeskcfg.egg-info/SOURCES.txt
zdeskcfg.egg-info/dependency_links.txt
zdeskcfg.egg-info/not-zip-safe
zdeskcfg.egg-info/requires.txt
zdeskcfg.egg-info/top_level.txt