Metadata-Version: 2.1
Name: zdeskcfg
Version: 2.0.0
Summary: Easy configuration of zendesk/zdesk scripts.
Home-page: http://github.com/fprimex/zdeskcfg
Author: Brent Woodruff
Author-email: brent@fprimex.com
License: BSD
Keywords: zendesk zdesk config
Classifier: Development Status :: 5 - Production/Stable
Classifier: Intended Audience :: Developers
Classifier: License :: OSI Approved :: BSD License
Classifier: Topic :: Software Development :: Libraries
License-File: LICENSE
Requires-Dist: plac_ini
